botorift/__init__.py
botorift/_modidx.py
botorift/azure_client.py
botorift-0.0.1.dist-info/LICENSE
botorift-0.0.1.dist-info/METADATA
botorift-0.0.1.dist-info/WHEEL
botorift-0.0.1.dist-info/entry_points.txt
botorift-0.0.1.dist-info/top_level.txt
botorift-0.0.1.dist-info/RECORD
